brazilian_holidays/__init__.py
brazilian_holidays/datas.py
brazilian_holidays-0.1.27.dist-info/licenses/LICENSE
brazilian_holidays-0.1.27.dist-info/METADATA
brazilian_holidays-0.1.27.dist-info/WHEEL
brazilian_holidays-0.1.27.dist-info/top_level.txt
brazilian_holidays-0.1.27.dist-info/RECORD
