Metadata-Version: 2.4
Name: brazilian-holidays
Version: 0.1.27
Summary: Brazilian Holidays
Author-email: Michel Metran <michelmetran@gmail.com>
License-Expression: MIT
Project-URL: Homepage, https://github.com/michelmetran/brazilian-holidays
Project-URL: Issues, https://github.com/michelmetran/brazilian-holidays/issues
Project-URL: Repository, https://github.com/michelmetran/brazilian-holidays
Project-URL: Documentation, https://brazilian-holidays.readthedocs.io
Keywords: holidays,feriados,brazilian
Requires-Python: >=3.11
License-File: LICENSE
Requires-Dist: holidays>=0.82
Requires-Dist: pandas>=2.2.2
Requires-Dist: tabulate>=0.9.0
Dynamic: license-file
